praatfan_gpl/__init__.py
praatfan_gpl/compat/__init__.py
praatfan_gpl/compat/parselmouth.py
praatfan_gpl/praatfan_gpl.cpython-312-darwin.so
praatfan_gpl-0.1.2.dist-info/METADATA
praatfan_gpl-0.1.2.dist-info/WHEEL
praatfan_gpl-0.1.2.dist-info/RECORD
