Metadata-Version: 2.4
Name: praatfan-gpl
Version: 0.1.2
Classifier: Development Status :: 4 - Beta
Classifier: Intended Audience :: Science/Research
Classifier: License :: OSI Approved :: GNU General Public License v3 (GPLv3)
Classifier: Operating System :: OS Independent
Classifier: Programming Language :: Python :: 3
Classifier: Programming Language :: Python :: 3.8
Classifier: Programming Language :: Python :: 3.9
Classifier: Programming Language :: Python :: 3.10
Classifier: Programming Language :: Python :: 3.11
Classifier: Programming Language :: Python :: 3.12
Classifier: Programming Language :: Rust
Classifier: Topic :: Multimedia :: Sound/Audio :: Analysis
Classifier: Topic :: Scientific/Engineering
Requires-Dist: numpy>=1.20
Requires-Dist: pytest>=7.0 ; extra == 'dev'
Requires-Dist: parselmouth>=0.4 ; extra == 'dev'
Provides-Extra: dev
Summary: Praat-compatible acoustic analysis in Python (Rust implementation)
Keywords: audio,speech,acoustics,praat,signal-processing,formant,pitch
License: GPL-3.0
Requires-Python: >=3.8
Project-URL: Repository, https://github.com/ucpresearch/praatfan-core-rs
